Metadata-Version: 2.1
Name: storage-manager
Version: 0.4.0
Summary: Storage - a load-balanced storage manager
Home-page: https://github.com/mandarons/storage-manager
Author: Mandar Patil
Author-email: mandarons@pm.me
License: UNKNOWN
Platform: UNKNOWN
Classifier: Programming Language :: Python :: 3
Classifier: Operating System :: OS Independent
Requires-Python: >=3.8
Requires-Dist: click (==7.1.2)
Requires-Dist: humanfriendly (==8.2)
Requires-Dist: python-dotenv (==0.15.0)
Requires-Dist: tabulate (==0.8.7)
Requires-Dist: tinydb (==4.2.0)
Requires-Dist: tqdm (==4.51.0)
